config_moxad/__init__.py
config_moxad/config.py
config_moxad-4.0.2.dist-info/METADATA
config_moxad-4.0.2.dist-info/WHEEL
config_moxad-4.0.2.dist-info/licenses/LICENSE.txt
config_moxad-4.0.2.dist-info/RECORD
