Metadata-Version: 2.1
Name: config_moxad
Version: 4.0.2
Summary: read non-ugly human-readable config files
Project-URL: Homepage, https://github.com/rjwhite/Python-config-module
Author-email: RJ White <rj.white@moxad.com>
License-File: LICENSE.txt
Classifier: Intended Audience :: Developers
Classifier: License :: OSI Approved :: GNU General Public License v3 (GPLv3)
Classifier: Natural Language :: English
Classifier: Operating System :: POSIX :: Linux
Classifier: Programming Language :: Python
Classifier: Programming Language :: Python :: 2
Classifier: Programming Language :: Python :: 3
